codex2mc/CLI.py
codex2mc/__init__.py
codex2mc/codex2mc.py
codex2mc/illumination_corr.py
codex2mc/json_parser.py
codex2mc/mc_tools.py
codex2mc/ome_schema.py
codex2mc/ome_writer.py
codex2mc/qc.py
codex2mc/templates.py
codex2mc/tools.py
codex2mc-0.0.3.dist-info/licenses/LICENSE
codex2mc-0.0.3.dist-info/METADATA
codex2mc-0.0.3.dist-info/WHEEL
codex2mc-0.0.3.dist-info/entry_points.txt
codex2mc-0.0.3.dist-info/top_level.txt
codex2mc-0.0.3.dist-info/RECORD
