Metadata-Version: 2.4
Name: codex2mc
Version: 0.0.3
Summary: stages CODEX data sets for being registered with ASHLAR in MCMICRO.
Author-email: Victor Perez <hhabraxas@gmail.com>, "Miguel A. Ibarra-Arellano" <c180l058j@mozmail.com>
License: BSD-3-Clause
Project-URL: Homepage, https://github.com/SchapiroLabor/codex2mc
Project-URL: Issues, https://github.com/SchapiroLabor/codex2mc/issues
Keywords: mcmicro,multiplex imaging,proteomics,CODEX,staging
Classifier: Programming Language :: Python :: 3.12
Classifier: Operating System :: OS Independent
Classifier: Intended Audience :: Science/Research
Classifier: License :: OSI Approved :: BSD License
Requires-Python: >=3.12
License-File: LICENSE
Requires-Dist: ome-types==0.5.2
Requires-Dist: numpy
Requires-Dist: tifffile
Requires-Dist: pandas
Requires-Dist: beautifulsoup4
Requires-Dist: BaSiCPy
Dynamic: license-file
